test/__init__.py
test/__main__.py
test/test_distributions.py
test/test_individuals.py
test/test_language.py
tyche/__init__.py
tyche/distributions.py
tyche/individuals.py
tyche/language.py
tyche/probability.py
tyche/references.py
Tyche-1.0.1.dist-info/LICENSE
Tyche-1.0.1.dist-info/METADATA
Tyche-1.0.1.dist-info/WHEEL
Tyche-1.0.1.dist-info/top_level.txt
Tyche-1.0.1.dist-info/zip-safe
Tyche-1.0.1.dist-info/RECORD
