Metadata-Version: 2.1
Name: Tyche
Version: 1.0.1
Summary: Tyche is a library to facilitate the use of aleatoric description logic to construct, query, and update probabilistic belief models.
Home-page: https://github.com/TycheLibrary/Tyche
Author: Paddy Lamont
Author-email: padraiglamont@gmail.com
License: MIT License
Keywords: probability,belief,knowledge-base,ontology,description-logic
Classifier: Programming Language :: Python :: 3
License-File: LICENSE
Requires-Dist: numpy
Requires-Dist: scipy
